{
  "appKey": "",
  "appSecret": "",
  "encryptJs": true,
  "excludeScenes": [],
  "fb-instant-games": {},
  "includeAnySDK": false,
  "includeSDKBox": false,
  "inlineSpriteFrames": true,
  "inlineSpriteFrames_native": true,
  "jailbreakPlatform": false,
  "md5Cache": false,
  "mergeStartScene": false,
  "oauthLoginServer": "",
  "optimizeHotUpdate": false,
  "orientation": {
    "landscapeLeft": true,
    "landscapeRight": true,
    "portrait": false,
    "upsideDown": false
  },
  "packageName": "org.cocos2d.XiYouLand",
  "privateKey": "",
  "qqplay": {
    "REMOTE_SERVER_ROOT": "",
    "orientation": "portrait"
  },
  "renderMode": "0",
  "startScene": "4667b05c-24f7-45c5-910e-283b393c4fe3",
  "title": "XiYouLand",
  "webOrientation": "auto",
  "wechatgame": {
    "REMOTE_SERVER_ROOT": "",
    "appid": "wx6ac3f5090a6b99c5",
    "isSubdomain": false,
    "orientation": "portrait",
    "subContext": ""
  },
  "xxteaKey": "07b1e25c-f0b7-4e",
  "zipCompressJs": true
}